AUTHORS
CHANGES
LICENSE
MANIFEST.in
README
setup.cfg
setup.py
KalaPy.egg-info/PKG-INFO
KalaPy.egg-info/SOURCES.txt
KalaPy.egg-info/dependency_links.txt
KalaPy.egg-info/not-zip-safe
KalaPy.egg-info/requires.txt
KalaPy.egg-info/top_level.txt
bin/kalapy-quickstart.py
docs/Makefile
docs/source/admin.rst
docs/source/conf.py
docs/source/deploying.rst
docs/source/gae.rst
docs/source/i18n.rst
docs/source/index.rst
docs/source/installation.rst
docs/source/introduction.rst
docs/source/license.rst
docs/source/package.rst
docs/source/settings.rst
docs/source/tutorial.rst
docs/source/_static/favicon.ico
docs/source/_static/wiki-extended.png
docs/source/_static/wiki.png
docs/source/_themes/peacock/layout.html
docs/source/_themes/peacock/theme.conf
docs/source/_themes/peacock/static/jquery.corner.js
docs/source/_themes/peacock/static/peacock.css_t
docs/source/_themes/peacock/static/peacock.js_t
docs/source/api/admin.rst
docs/source/api/db.rst
docs/source/api/i18n.rst
docs/source/api/signals.rst
docs/source/api/utils.rst
docs/source/api/web.rst
example/README.txt
example/admin.py
example/app.yaml
example/gaehandler.py
example/index.yaml
example/settings.py
example/main/__init__.py
example/main/models.py
example/main/tests.py
example/main/views.py
example/main/locale/messages.pot
example/main/locale/de_DE/LC_MESSAGES/messages.po
example/main/locale/es_ES/LC_MESSAGES/messages.po
example/main/locale/fr_FR/LC_MESSAGES/messages.po
example/main/static/favicon.ico
example/main/static/robots.txt
example/main/static/style.css
example/main/templates/index.html
example/static/favicon.ico
example/static/robots.txt
example/wiki/__init__.py
example/wiki/models.py
example/wiki/settings.py
example/wiki/tests.py
example/wiki/views.py
example/wiki/locale/messages.pot
example/wiki/locale/de_DE/LC_MESSAGES/messages.po
example/wiki/locale/es_ES/LC_MESSAGES/messages.po
example/wiki/locale/fr_FR/LC_MESSAGES/messages.po
example/wiki/static/style.css
example/wiki/templates/changes.html
example/wiki/templates/diff.html
example/wiki/templates/edit.html
example/wiki/templates/index.html
example/wiki/templates/layout.html
example/wiki/templates/log.html
